{
  "Untitled design.png": {
    "mime": "image/png"
  },
  "About me.png": {
    "mime": "image/png"
  },
  "lines.png": {
    "mime": "image/png"
  },
  "line 2.png": {
    "mime": "image/png"
  },
  "14.png": {
    "mime": "image/png"
  },
  "34.png": {
    "mime": "image/png"
  },
  "About me (1).png": {
    "mime": "image/png"
  },
  "Green Gradient Application Showcase Presentation.jpg": {
    "mime": "image/jpeg"
  },
  "LekhArt.png": {
    "mime": "image/png"
  },
  "QR scanner.png": {
    "mime": "image/png"
  },
  "image.jpg": {
    "mime": "image/jpeg"
  },
  "ux-design.png": {
    "mime": "image/png"
  },
  "prototype.png": {
    "mime": "image/png"
  },
  "product.png": {
    "mime": "image/png"
  },
  "ux.png": {
    "mime": "image/png"
  },
  "app-store.png": {
    "mime": "image/png"
  },
  "logo.png": {
    "mime": "image/png"
  },
  "animation.png": {
    "mime": "image/png"
  },
  "facebook-app-symbol.png": {
    "mime": "image/png"
  },
  "instagram.png": {
    "mime": "image/png"
  },
  "linkedin.png": {
    "mime": "image/png"
  },
  "github.png": {
    "mime": "image/png"
  },
  "idea.png": {
    "mime": "image/png"
  },
  "teamwork.png": {
    "mime": "image/png"
  },
  "ok.png": {
    "mime": "image/png"
  },
  "growth.png": {
    "mime": "image/png"
  },
  "Simulator Screen Shot - iPhone 14 Pro - 2022-09-24 at 09.01.48.png": {
    "mime": "image/png"
  },
  "Simulator Screen Shot - iPhone 14 Pro - 2022-09-24 at 09.02.09.png": {
    "mime": "image/png"
  }
}